thedus/__init__.py
thedus/base_migration.py
thedus/env_manager.py
thedus/migration_file_manager.py
thedus/run.py
thedus/cmd/__init__.py
thedus/cmd/abstract_cmd.py
thedus/cmd/clickhouse_cmd.py
thedus-0.2.0b0.dist-info/licenses/LICENSE
thedus-0.2.0b0.dist-info/METADATA
thedus-0.2.0b0.dist-info/WHEEL
thedus-0.2.0b0.dist-info/entry_points.txt
thedus-0.2.0b0.dist-info/top_level.txt
thedus-0.2.0b0.dist-info/RECORD
